rhkpy/__init__.py
rhkpy/rhkpy_loader.py
rhkpy/rhkpy_process.py
rhkpy/version.py
spym/__init__.py
spym/_version.py
spym/_accessors/__init__.py
spym/io/__init__.py
spym/io/load.py
spym/io/omicronscala/__init__.py
spym/io/omicronscala/_methods.py
spym/io/omicronscala/_scala.py
spym/io/rhksm4/__init__.py
spym/io/rhksm4/_methods.py
spym/io/rhksm4/_sm4.py
spym/plotting/__init__.py
spym/process/__init__.py
spym/process/filters.py
spym/process/level.py
rhkpy-1.3.9.dist-info/LICENSE
rhkpy-1.3.9.dist-info/METADATA
rhkpy-1.3.9.dist-info/WHEEL
rhkpy-1.3.9.dist-info/top_level.txt
rhkpy-1.3.9.dist-info/RECORD
