Metadata-Version: 2.1
Name: rhkpy
Version: 1.3.9
Summary: A python package for processing Scanning Tunneling Microscopy (STM) data from RHK, based on the spym project.
Home-page: https://github.com/zrbyte/rhkpy
Author: Peter Nemes-Incze
Classifier: License :: OSI Approved :: MIT License
Classifier: Programming Language :: Python :: 3
Classifier: Operating System :: OS Independent
License-File: LICENSE
Requires-Dist: matplotlib
Requires-Dist: numpy
Requires-Dist: pandas
Requires-Dist: scipy
Requires-Dist: xarray >=2023.7.0
Requires-Dist: holoviews >=1.17.0
Requires-Dist: hvplot >=0.8.4
Requires-Dist: bokeh >=3.2.2
Requires-Dist: panel >=1.2.1
Requires-Dist: selenium
